zinnia_bitly/__init__.py
zinnia_url_shortener_bitly-1.1.dist-info/metadata.json
zinnia_url_shortener_bitly-1.1.dist-info/top_level.txt
zinnia_url_shortener_bitly-1.1.dist-info/DESCRIPTION.rst
zinnia_url_shortener_bitly-1.1.dist-info/RECORD
zinnia_url_shortener_bitly-1.1.dist-info/METADATA
zinnia_url_shortener_bitly-1.1.dist-info/WHEEL
