Metadata-Version: 2.0
Name: zinnia-url-shortener-bitly
Version: 1.1
Summary: Bit.ly URL shortener backend for django-blog-zinnia
Home-page: https://github.com/Fantomas42/zinnia-url-shortener-bitly
Author: Fantomas42
Author-email: fantomas42@gmail.com
License: BSD License
Keywords: django,zinnia,url,bit.ly
Platform: UNKNOWN
Classifier: Framework :: Django
Classifier: Development Status :: 5 - Production/Stable
Classifier: Environment :: Web Environment
Classifier: Programming Language :: Python
Classifier: Intended Audience :: Developers
Classifier: Operating System :: OS Independent
Classifier: License :: OSI Approved :: BSD License
Classifier: Topic :: Software Development :: Libraries :: Python Modules
Requires-Dist: django-bitly
